{
  "main": {
    "id": "d1773adbb4c40e3b",
    "type": "split",
    "children": [
      {
        "id": "43c0b7430e85da82",
        "type": "tabs",
        "children": [
          {
            "id": "ed04283a100bd5ad",
            "type": "leaf",
            "state": {
              "type": "markdown",
              "state": {
                "file": "README.md",
                "mode": "source",
                "source": false
              }
            }
          },
          {
            "id": "45e01da171c4f202",
            "type": "leaf",
            "state": {
              "type": "markdown",
              "state": {
                "file": "migrate-file.md",
                "mode": "source",
                "source": false
              }
            }
          },
          {
            "id": "992aa417427e20b7",
            "type": "leaf",
            "state": {
              "type": "markdown",
              "state": {
                "file": "migrate-file.md",
                "mode": "source",
                "source": false
              }
            }
          },
          {
            "id": "bdf8060f6380627a",
            "type": "leaf",
            "state": {
              "type": "markdown",
              "state": {
                "file": "vim notes.md",
                "mode": "source",
                "source": false
              }
            }
          },
          {
            "id": "7ca6fde180ac5852",
            "type": "leaf",
            "state": {
              "type": "markdown",
              "state": {
                "file": "algorithm/README.MD.md",
                "mode": "source",
                "source": false
              }
            }
          }
        ],
        "currentTab": 4
      }
    ],
    "direction": "vertical"
  },
  "left": {
    "id": "84f9de077326c312",
    "type": "split",
    "children": [
      {
        "id": "0857aa722570d417",
        "type": "tabs",
        "children": [
          {
            "id": "5bd5bdfcf1556012",
            "type": "leaf",
            "state": {
              "type": "file-explorer",
              "state": {
                "sortOrder": "alphabetical"
              }
            }
          },
          {
            "id": "db6fac30f4a8da5f",
            "type": "leaf",
            "state": {
              "type": "search",
              "state": {
                "query": "",
                "matchingCase": false,
                "explainSearch": false,
                "collapseAll": false,
                "extraContext": false,
                "sortOrder": "alphabetical"
              }
            }
          },
          {
            "id": "5e77fc6cf2805383",
            "type": "leaf",
            "state": {
              "type": "starred",
              "state": {}
            }
          }
        ]
      }
    ],
    "direction": "horizontal",
    "width": 300
  },
  "right": {
    "id": "463eaadcb39809fb",
    "type": "split",
    "children": [
      {
        "id": "83948116fcba51e8",
        "type": "tabs",
        "children": [
          {
            "id": "66cd542beb6a8ca4",
            "type": "leaf",
            "state": {
              "type": "backlink",
              "state": {
                "file": "algorithm/README.MD.md",
                "collapseAll": false,
                "extraContext": false,
                "sortOrder": "alphabetical",
                "showSearch": false,
                "searchQuery": "",
                "backlinkCollapsed": false,
                "unlinkedCollapsed": true
              }
            }
          },
          {
            "id": "914b4ccd56fa4afb",
            "type": "leaf",
            "state": {
              "type": "outgoing-link",
              "state": {
                "file": "algorithm/README.MD.md",
                "linksCollapsed": false,
                "unlinkedCollapsed": true
              }
            }
          },
          {
            "id": "d1b834d5bb40c4ff",
            "type": "leaf",
            "state": {
              "type": "tag",
              "state": {
                "sortOrder": "frequency",
                "useHierarchy": true
              }
            }
          },
          {
            "id": "b65294ecee9a74f8",
            "type": "leaf",
            "state": {
              "type": "outline",
              "state": {
                "file": "algorithm/README.MD.md"
              }
            }
          }
        ]
      }
    ],
    "direction": "horizontal",
    "width": 300,
    "collapsed": true
  },
  "left-ribbon": {
    "hiddenItems": {
      "canvas:新建白板": false,
      "switcher:打开快速切换": false,
      "graph:查看关系图谱": false,
      "daily-notes:打开/创建今天的日记": false,
      "templates:插入模板": false,
      "command-palette:打开命令面板": false
    }
  },
  "active": "5bd5bdfcf1556012",
  "lastOpenFiles": [
    "vim notes.md",
    "algorithm/README.MD.md",
    "algorithm",
    "migrate-file.md",
    "README.md"
  ]
}